rtl/ahb_apb_bridge.sv
// AHB-to-APB Bridge — iverilog compatible version
// Saras Chandra Kannam — personal portfolio
//
// Bridges an AHB master to up to 4 APB peripherals.
// FSM: IDLE -> SAMPLE -> SETUP -> ENABLE -> RESP -> IDLE
//
// APB slave address map (default):
//   Slave 0: 0x4000_xxxx
//   Slave 1: 0x4001_xxxx
//   Slave 2: 0x4002_xxxx
//   Slave 3: 0x4003_xxxx
//
// TODO: burst support (HBURST), HRESP ERROR on unmapped address
// FIXME: single-cycle SAMPLE state adds one extra wait cycle — could
//        optimize to go IDLE->SETUP directly for registered decoders

`timescale 1ns/1ps

module ahb_apb_bridge #(
    parameter ADDR_WIDTH = 32,
    parameter DATA_WIDTH = 32,
    parameter NUM_SLAVES = 4,
    // flat packed slave base addresses — 4 x 32-bit, index 0 at MSB
    parameter [NUM_SLAVES*ADDR_WIDTH-1:0] SLAVE_BASES =
        {32'h4003_0000, 32'h4002_0000, 32'h4001_0000, 32'h4000_0000},
    parameter [ADDR_WIDTH-1:0] SLAVE_MASK = 32'hFFFF_0000
)(
    input  wire                  HCLK, HRESETn,
    input  wire                  HSEL,
    input  wire                  HREADY_IN,
    input  wire [1:0]            HTRANS,
    input  wire                  HWRITE,
    input  wire [ADDR_WIDTH-1:0] HADDR,
    input  wire [DATA_WIDTH-1:0] HWDATA,
    output reg  [DATA_WIDTH-1:0] HRDATA,
    output wire                  HREADY,
    output reg                   HRESP,

    output reg  [ADDR_WIDTH-1:0] PADDR,
    output reg                   PWRITE,
    output reg  [DATA_WIDTH-1:0] PWDATA,
    output reg  [NUM_SLAVES-1:0] PSEL,
    output reg                   PENABLE,
    input  wire [DATA_WIDTH-1:0] PRDATA,
    input  wire                  PREADY,
    input  wire                  PSLVERR
);

    localparam HTRANS_NONSEQ = 2'b10;

    // FSM states
    localparam [2:0]
        ST_IDLE    = 3'd0,
        ST_SAMPLE  = 3'd1,
        ST_SETUP   = 3'd2,
        ST_ENABLE  = 3'd3,
        ST_RESP    = 3'd4;

    reg [2:0] state, next_state;

    // saved AHB request
    reg [ADDR_WIDTH-1:0] saved_addr;
    reg [DATA_WIDTH-1:0] saved_wdata;
    reg                  saved_write;
    reg [NUM_SLAVES-1:0] saved_sel;

    // decode slave select from HADDR
    reg [NUM_SLAVES-1:0] slave_sel;
    integer k;
    always @(*) begin
        slave_sel = {NUM_SLAVES{1'b0}};
        for (k = 0; k < NUM_SLAVES; k = k + 1) begin
            if ((HADDR & SLAVE_MASK) ==
                (SLAVE_BASES[k*ADDR_WIDTH +: ADDR_WIDTH] & SLAVE_MASK))
                slave_sel[k] = 1'b1;
        end
    end

    // state register
    always @(posedge HCLK or negedge HRESETn) begin
        if (!HRESETn) state <= ST_IDLE;
        else          state <= next_state;
    end

    // next-state logic
    always @(*) begin
        next_state = state;
        case (state)
            ST_IDLE:    if (HSEL && HREADY_IN && HTRANS == HTRANS_NONSEQ)
                            next_state = ST_SAMPLE;
            ST_SAMPLE:  next_state = ST_SETUP;
            ST_SETUP:   next_state = ST_ENABLE;
            ST_ENABLE:  if (PREADY) next_state = ST_RESP;
            ST_RESP:    next_state = ST_IDLE;
            default:    next_state = ST_IDLE;
        endcase
    end

    // latch AHB request across two clock cycles:
    //   address phase (IDLE): capture HADDR/HWRITE/PSEL
    //   data phase (SAMPLE):  capture HWDATA (valid one cycle after address)
    always @(posedge HCLK or negedge HRESETn) begin
        if (!HRESETn) begin
            saved_addr  <= {ADDR_WIDTH{1'b0}};
            saved_wdata <= {DATA_WIDTH{1'b0}};
            saved_write <= 1'b0;
            saved_sel   <= {NUM_SLAVES{1'b0}};
        end else begin
            if (state == ST_IDLE && HSEL && HREADY_IN && HTRANS == HTRANS_NONSEQ) begin
                saved_addr  <= HADDR;
                saved_write <= HWRITE;
                saved_sel   <= slave_sel;
                // Note: DON'T capture HWDATA here — it's the previous cycle's data.
                // AHB write data is valid in the DATA phase (ST_SAMPLE).
            end
            if (state == ST_SAMPLE) begin
                saved_wdata <= HWDATA;  // now valid: data phase of AHB write
            end
        end
    end

    // APB outputs
    always @(posedge HCLK or negedge HRESETn) begin
        if (!HRESETn) begin
            PADDR   <= {ADDR_WIDTH{1'b0}};
            PWRITE  <= 1'b0;
            PWDATA  <= {DATA_WIDTH{1'b0}};
            PSEL    <= {NUM_SLAVES{1'b0}};
            PENABLE <= 1'b0;
            HRDATA  <= {DATA_WIDTH{1'b0}};
            HRESP   <= 1'b0;
        end else begin
            PSEL    <= {NUM_SLAVES{1'b0}};
            PENABLE <= 1'b0;
            HRESP   <= PSLVERR;
            case (state)
                ST_SAMPLE: begin
                    PADDR  <= saved_addr;
                    PWRITE <= saved_write;
                    // Note: don't assign PWDATA here — saved_wdata is latched
                    // at the same edge (NBA race). Use HWDATA directly in ST_SETUP.
                end
                ST_SETUP: begin
                    // HWDATA is still valid here: AHB master holds it stable
                    // until HREADY, which we deassert throughout the APB transfer.
                    PWDATA  <= HWDATA;
                    PSEL    <= saved_sel;
                    PENABLE <= 1'b0;
                end
                ST_ENABLE: begin
                    PSEL    <= saved_sel;
                    PENABLE <= 1'b1;
                    // Capture HRDATA while PSEL is still asserted (PRDATA valid).
                    // Can't do it in ST_RESP because PSEL is cleared by default above.
                    if (PREADY)
                        HRDATA <= PRDATA;
                end
                ST_RESP: ; // HRDATA already captured in ST_ENABLE
            endcase
        end
    end

    // HREADY low while APB transaction is in flight
    assign HREADY = (state == ST_IDLE || state == ST_RESP);

endmodule

tb/tb_top.sv
// Simulation top — iverilog compatible (no always_ff, no unpacked param arrays)
`timescale 1ns/1ps

module tb_top;
    reg         HCLK;
    reg         HRESETn;
    reg         HSEL;
    reg         HREADY_IN;
    reg  [1:0]  HTRANS;
    reg         HWRITE;
    reg  [31:0] HADDR;
    reg  [31:0] HWDATA;
    wire [31:0] HRDATA;
    wire        HREADY;
    wire        HRESP;
    wire [31:0] PADDR;
    wire        PWRITE;
    wire [31:0] PWDATA;
    wire [3:0]  PSEL;
    wire        PENABLE;
    reg  [31:0] PRDATA;
    reg         PREADY;
    reg         PSLVERR;

    // Per-slave memory — 4 slaves × 256 words
    // PSEL[i] determines which slave is active; PADDR[9:2] is the word index.
    reg [31:0] slave_mem [0:3][0:255];
    integer    s;

    always @(posedge HCLK) begin
        if (PENABLE && PWRITE) begin
            for (s = 0; s < 4; s = s + 1)
                if (PSEL[s]) slave_mem[s][PADDR[9:2]] <= PWDATA;
        end
    end

    always @(*) begin
        PRDATA = 32'h0;
        for (s = 0; s < 4; s = s + 1)
            if (PSEL[s]) PRDATA = slave_mem[s][PADDR[9:2]];
    end
    initial PREADY  = 1;
    initial PSLVERR = 0;

    ahb_apb_bridge dut (
        .HCLK(HCLK), .HRESETn(HRESETn),
        .HSEL(HSEL), .HREADY_IN(HREADY_IN),
        .HTRANS(HTRANS), .HWRITE(HWRITE),
        .HADDR(HADDR), .HWDATA(HWDATA),
        .HRDATA(HRDATA), .HREADY(HREADY), .HRESP(HRESP),
        .PADDR(PADDR), .PWRITE(PWRITE), .PWDATA(PWDATA),
        .PSEL(PSEL), .PENABLE(PENABLE),
        .PRDATA(PRDATA), .PREADY(PREADY), .PSLVERR(PSLVERR)
    );

    initial HCLK = 0;
    always #5 HCLK = ~HCLK;

    initial begin
        $dumpfile("waves.vcd");
        $dumpvars(0, tb_top);
    end
endmodule

sim/waves.vcd
$date
	Sun May 10 11:06:46 2026
$end
$version
	Icarus Verilog
$end
$timescale
	1ps
$end
$scope module tb_top $end
$var wire 1 ! PWRITE $end
$var wire 32 " PWDATA [31:0] $end
$var wire 4 # PSEL [3:0] $end
$var wire 1 $ PENABLE $end
$var wire 32 % PADDR [31:0] $end
$var wire 1 & HRESP $end
$var wire 1 ' HREADY $end
$var wire 32 ( HRDATA [31:0] $end
$var reg 32 ) HADDR [31:0] $end
$var reg 1 * HCLK $end
$var reg 1 + HREADY_IN $end
$var reg 1 , HRESETn $end
$var reg 1 - HSEL $end
$var reg 2 . HTRANS [1:0] $end
$var reg 32 / HWDATA [31:0] $end
$var reg 1 0 HWRITE $end
$var reg 32 1 PRDATA [31:0] $end
$var reg 1 2 PREADY $end
$var reg 1 3 PSLVERR $end
$var integer 32 4 s [31:0] $end
$scope module dut $end
$var wire 32 5 HADDR [31:0] $end
$var wire 1 * HCLK $end
$var wire 1 ' HREADY $end
$var wire 1 + HREADY_IN $end
$var wire 1 , HRESETn $end
$var wire 1 - HSEL $end
$var wire 2 6 HTRANS [1:0] $end
$var wire 32 7 HWDATA [31:0] $end
$var wire 1 0 HWRITE $end
$var wire 32 8 PRDATA [31:0] $end
$var wire 1 2 PREADY $end
$var wire 1 3 PSLVERR $end
$var parameter 32 9 ADDR_WIDTH $end
$var parameter 32 : DATA_WIDTH $end
$var parameter 2 ; HTRANS_NONSEQ $end
$var parameter 32 < NUM_SLAVES $end
$var parameter 128 = SLAVE_BASES $end
$var parameter 32 > SLAVE_MASK $end
$var parameter 3 ? ST_ENABLE $end
$var parameter 3 @ ST_IDLE $end
$var parameter 3 A ST_RESP $end
$var parameter 3 B ST_SAMPLE $end
$var parameter 3 C ST_SETUP $end
$var reg 32 D HRDATA [31:0] $end
$var reg 1 & HRESP $end
$var reg 32 E PADDR [31:0] $end
$var reg 1 $ PENABLE $end
$var reg 4 F PSEL [3:0] $end
$var reg 32 G PWDATA [31:0] $end
$var reg 1 ! PWRITE $end
$var reg 3 H next_state [2:0] $end
$var reg 32 I saved_addr [31:0] $end
$var reg 4 J saved_sel [3:0] $end
$var reg 32 K saved_wdata [31:0] $end
$var reg 1 L saved_write $end
$var reg 4 M slave_sel [3:0] $end
$var reg 3 N state [2:0] $end
$var integer 32 O k [31:0] $end
$upscope $end
$upscope $end
$enddefinitions $end
$comment Show the parameter values. $end
$dumpall
b10 C
b1 B
b100 A
b0 @
b11 ?
b11111111111111110000000000000000 >
b1000000000000110000000000000000010000000000001000000000000000000100000000000001000000000000000001000000000000000000000000000000 =
b100 <
b10 ;
b100000 :
b100000 9
$end
#0
$dumpvars
b100 O
b0 N
b0 M
0L
b0 K
b0 J
b0 I
b0 H
b0 G
b0 F
b0 E
b0 D
b0 8
b0 7
b0 6
b0 5
b100 4
03
12
b0 1
00
b0 /
b0 .
0-
0,
1+
1*
b0 )
b0 (
1'
0&
b0 %
0$
b0 #
b0 "
0!
$end
#5000
0*
#10000
1*
#15000
0*
#20000
1*
#25000
0*
#30000
1*
#35000
0*
#40000
1,
1*
#45000
0*
#50000
b1 M
b100 O
b1 H
b1000000000000000000000000000000 )
b1000000000000000000000000000000 5
10
b10 .
b10 6
1-
1*
#55000
0*
#60000
0-
b0 .
b0 6
b11011110101011010000000000000000 /
b11011110101011010000000000000000 7
b10 H
0'
b1 N
b1 J
1L
b1000000000000000000000000000000 I
1*
#65000
0*
#70000
b100 4
b11 H
1!
b1000000000000000000000000000000 %
b1000000000000000000000000000000 E
b11011110101011010000000000000000 K
b10 N
1*
#75000
0*
#80000
b100 H
bx 1
bx 8
b100 4
b11 N
b1 #
b1 F
b11011110101011010000000000000000 "
b11011110101011010000000000000000 G
1*
#85000
0*
#90000
b100 4
bx 1
bx 8
b0 H
1'
bx (
bx D
1$
b1 #
b1 F
b100 N
1*
#95000
0*
#100000
b100 O
b10 M
b1 H
b1000000000000010000000000010000 )
b1000000000000010000000000010000 5
b10 .
b10 6
1-
b0 1
b0 8
b0 N
0$
b0 #
b0 F
b100 4
1*
#105000
0*
#110000
0-
b0 .
b0 6
b11011110101011010000000000000001 /
b11011110101011010000000000000001 7
b10 H
0'
b10 J
b1000000000000010000000000010000 I
b1 N
1*
#115000
0*
#120000
b11 H
b100 4
b10 N
b11011110101011010000000000000001 K
b1000000000000010000000000010000 %
b1000000000000010000000000010000 E
1*
#125000
0*
#130000
bx 1
bx 8
b100 4
b100 H
b10 #
b10 F
b11011110101011010000000000000001 "
b11011110101011010000000000000001 G
b11 N
1*
#135000
0*
#140000
b0 H
1'
b100 4
bx 1
bx 8
b100 N
1$
b10 #
b10 F
1*
#145000
0*
#150000
b100 O
b100 M
b1 H
b1000000000000100000000000100000 )
b1000000000000100000000000100000 5
b10 .
b10 6
1-
b0 1
b0 8
0$
b0 #
b0 F
b0 N
b100 4
1*
#155000
0*
#160000
0-
b0 .
b0 6
b11011110101011010000000000000010 /
b11011110101011010000000000000010 7
b10 H
0'
b1 N
b100 J
b1000000000000100000000000100000 I
1*
#165000
0*
#170000
b100 4
b11 H
b1000000000000100000000000100000 %
b1000000000000100000000000100000 E
b11011110101011010000000000000010 K
b10 N
1*
#175000
0*
#180000
b100 H
bx 1
bx 8
b100 4
b11 N
b100 #
b100 F
b11011110101011010000000000000010 "
b11011110101011010000000000000010 G
1*
#185000
0*
#190000
b100 4
bx 1
bx 8
b0 H
1'
1$
b100 #
b100 F
b100 N
1*
#195000
0*
#200000
b100 O
b1000 M
b1 H
b1000000000000110000000000110000 )
b1000000000000110000000000110000 5
b10 .
b10 6
1-
b0 1
b0 8
b0 N
0$
b0 #
b0 F
b100 4
1*
#205000
0*
#210000
0-
b0 .
b0 6
b11011110101011010000000000000011 /
b11011110101011010000000000000011 7
b10 H
0'
b1000 J
b1000000000000110000000000110000 I
b1 N
1*
#215000
0*
#220000
b11 H
b100 4
b10 N
b11011110101011010000000000000011 K
b1000000000000110000000000110000 %
b1000000000000110000000000110000 E
1*
#225000
0*
#230000
bx 1
bx 8
b100 4
b100 H
b1000 #
b1000 F
b11011110101011010000000000000011 "
b11011110101011010000000000000011 G
b11 N
1*
#235000
0*
#240000
b0 H
1'
b100 4
bx 1
bx 8
b100 N
1$
b1000 #
b1000 F
1*
#245000
0*
#250000
b0 1
b0 8
0$
b0 #
b0 F
b0 N
b100 4
1*
#250001
b100 4
b0 J
0L
b0 K
b0 I
b0 (
b0 D
b0 "
b0 G
0!
b0 %
b0 E
b100 O
b0 M
b0 /
b0 7
b0 )
b0 5
00
0,
#255000
0*
#260000
1*
#265000
0*
#270000
1*
#275000
0*
#280000
1*
#285000
0*
#290000
1*
#295000
0*
#300000
1,
1*
#305000
0*
#310000
b1 M
b100 O
b1 H
b1000000000000000000000000000100 )
b1000000000000000000000000000100 5
10
b10 .
b10 6
1-
1*
#315000
0*
#320000
0-
b0 .
b0 6
b10100101101001010000000000000000 /
b10100101101001010000000000000000 7
b10 H
0'
b1 J
1L
b1000000000000000000000000000100 I
b1 N
1*
#325000
0*
#330000
b11 H
b100 4
b10 N
b10100101101001010000000000000000 K
1!
b1000000000000000000000000000100 %
b1000000000000000000000000000100 E
1*
#335000
0*
#340000
bx 1
bx 8
b100 4
b100 H
b1 #
b1 F
b10100101101001010000000000000000 "
b10100101101001010000000000000000 G
b11 N
1*
#345000
0*
#350000
b0 H
1'
b100 4
bx 1
bx 8
b100 N
bx (
bx D
1$
b1 #
b1 F
1*
#355000
0*
#360000
b100 O
b10 M
b1 H
b1000000000000010000000000000100 )
b1000000000000010000000000000100 5
b10 .
b10 6
1-
b0 1
b0 8
0$
b0 #
b0 F
b0 N
b100 4
1*
#365000
0*
#370000
0-
b0 .
b0 6
b10100101101001010000000100000000 /
b10100101101001010000000100000000 7
b10 H
0'
b1 N
b10 J
b1000000000000010000000000000100 I
1*
#375000
0*
#380000
b100 4
b11 H
b1000000000000010000000000000100 %
b1000000000000010000000000000100 E
b10100101101001010000000100000000 K
b10 N
1*
#385000
0*
#390000
b100 H
bx 1
bx 8
b100 4
b11 N
b10 #
b10 F
b10100101101001010000000100000000 "
b10100101101001010000000100000000 G
1*
#395000
0*
#400000
b100 4
bx 1
bx 8
b0 H
1'
1$
b10 #
b10 F
b100 N
1*
#405000
0*
#410000
b100 O
b100 M
b1 H
b1000000000000100000000000000100 )
b1000000000000100000000000000100 5
b10 .
b10 6
1-
b0 1
b0 8
b0 N
0$
b0 #
b0 F
b100 4
1*
#415000
0*
#420000
0-
b0 .
b0 6
b10100101101001010000001000000000 /
b10100101101001010000001000000000 7
b10 H
0'
b100 J
b1000000000000100000000000000100 I
b1 N
1*
#425000
0*
#430000
b11 H
b100 4
b10 N
b10100101101001010000001000000000 K
b1000000000000100000000000000100 %
b1000000000000100000000000000100 E
1*
#435000
0*
#440000
bx 1
bx 8
b100 4
b100 H
b100 #
b100 F
b10100101101001010000001000000000 "
b10100101101001010000001000000000 G
b11 N
1*
#445000
0*
#450000
b0 H
1'
b100 4
bx 1
bx 8
b100 N
1$
b100 #
b100 F
1*
#455000
0*
#460000
b100 O
b1000 M
b1 H
b1000000000000110000000000000100 )
b1000000000000110000000000000100 5
b10 .
b10 6
1-
b0 1
b0 8
0$
b0 #
b0 F
b0 N
b100 4
1*
#465000
0*
#470000
0-
b0 .
b0 6
b10100101101001010000001100000000 /
b10100101101001010000001100000000 7
b10 H
0'
b1 N
b1000 J
b1000000000000110000000000000100 I
1*
#475000
0*
#480000
b100 4
b11 H
b1000000000000110000000000000100 %
b1000000000000110000000000000100 E
b10100101101001010000001100000000 K
b10 N
1*
#485000
0*
#490000
b100 H
bx 1
bx 8
b100 4
b11 N
b1000 #
b1000 F
b10100101101001010000001100000000 "
b10100101101001010000001100000000 G
1*
#495000
0*
#500000
b100 4
bx 1
bx 8
b0 H
1'
1$
b1000 #
b1000 F
b100 N
1*
#505000
0*
#510000
b100 O
b1 M
b1 H
b1000000000000000000000000000100 )
b1000000000000000000000000000100 5
00
b10 .
b10 6
1-
b0 1
b0 8
b0 N
0$
b0 #
b0 F
b100 4
1*
#515000
0*
#520000
0-
b0 .
b0 6
b10 H
0'
b1 J
0L
b1000000000000000000000000000100 I
b1 N
1*
#525000
0*
#530000
b11 H
b100 4
b10 N
0!
b1000000000000000000000000000100 %
b1000000000000000000000000000100 E
1*
#535000
0*
#540000
b10100101101001010000000000000000 1
b10100101101001010000000000000000 8
b100 4
b100 H
b1 #
b1 F
b11 N
1*
#545000
0*
#550000
b0 H
1'
b100 4
b10100101101001010000000000000000 1
b10100101101001010000000000000000 8
b100 N
b10100101101001010000000000000000 (
b10100101101001010000000000000000 D
1$
b1 #
b1 F
1*
#555000
0*
#560000
b100 O
b10 M
b1 H
b1000000000000010000000000000100 )
b1000000000000010000000000000100 5
b10 .
b10 6
1-
b100 4
b0 1
b0 8
0$
b0 #
b0 F
b0 N
1*
#565000
0*
#570000
0-
b0 .
b0 6
b10 H
0'
b1 N
b10 J
b1000000000000010000000000000100 I
1*
#575000
0*
#580000
b100 4
b11 H
b1000000000000010000000000000100 %
b1000000000000010000000000000100 E
b10 N
1*
#585000
0*
#590000
b100 H
b10100101101001010000000100000000 1
b10100101101001010000000100000000 8
b100 4
b11 N
b10 #
b10 F
1*
#595000
0*
#600000
b100 4
b10100101101001010000000100000000 1
b10100101101001010000000100000000 8
b0 H
1'
b10100101101001010000000100000000 (
b10100101101001010000000100000000 D
1$
b10 #
b10 F
b100 N
1*
#605000
0*
#610000
b100 O
b100 M
b1 H
b1000000000000100000000000000100 )
b1000000000000100000000000000100 5
b10 .
b10 6
1-
b100 4
b0 1
b0 8
b0 N
0$
b0 #
b0 F
1*
#615000
0*
#620000
0-
b0 .
b0 6
b10 H
0'
b100 J
b1000000000000100000000000000100 I
b1 N
1*
#625000
0*
#630000
b11 H
b100 4
b10 N
b1000000000000100000000000000100 %
b1000000000000100000000000000100 E
1*
#635000
0*
#640000
b10100101101001010000001000000000 1
b10100101101001010000001000000000 8
b100 4
b100 H
b100 #
b100 F
b11 N
1*
#645000
0*
#650000
b0 H
1'
b100 4
b10100101101001010000001000000000 1
b10100101101001010000001000000000 8
b100 N
b10100101101001010000001000000000 (
b10100101101001010000001000000000 D
1$
b100 #
b100 F
1*
#655000
0*
#660000
b100 O
b1000 M
b1 H
b1000000000000110000000000000100 )
b1000000000000110000000000000100 5
b10 .
b10 6
1-
b100 4
b0 1
b0 8
0$
b0 #
b0 F
b0 N
1*
#665000
0*
#670000
0-
b0 .
b0 6
b10 H
0'
b1 N
b1000 J
b1000000000000110000000000000100 I
1*
#675000
0*
#680000
b100 4
b11 H
b1000000000000110000000000000100 %
b1000000000000110000000000000100 E
b10 N
1*
#685000
0*
#690000
b100 H
b10100101101001010000001100000000 1
b10100101101001010000001100000000 8
b100 4
b11 N
b1000 #
b1000 F
1*
#695000
0*
#700000
b100 4
b10100101101001010000001100000000 1
b10100101101001010000001100000000 8
b0 H
1'
b10100101101001010000001100000000 (
b10100101101001010000001100000000 D
1$
b1000 #
b1000 F
b100 N
1*
#705000
0*
#710000
b100 4
b0 1
b0 8
b0 N
0$
b0 #
b0 F
1*
#710001
b100 4
b0 (
b0 D
b0 "
b0 G
b0 %
b0 E
b0 J
b0 K
b0 I
b100 O
b0 M
b0 /
b0 7
b0 )
b0 5
0,
#715000
0*
#720000
1*
#725000
0*
#730000
1*
#735000
0*
#740000
1*
#745000
0*
#750000
1*
#755000
0*
#760000
1,
1*
#765000
0*
#770000
b1 M
b100 O
b1 H
b1000000000000000000000000101100 )
b1000000000000000000000000101100 5
10
b10 .
b10 6
1-
1*
#775000
0*
#780000
0-
b0 .
b0 6
b1011101111011010001011011000100 /
b1011101111011010001011011000100 7
b10 H
0'
b1 N
b1 J
1L
b1000000000000000000000000101100 I
1*
#785000
0*
#790000
b100 4
b11 H
1!
b1000000000000000000000000101100 %
b1000000000000000000000000101100 E
b1011101111011010001011011000100 K
b10 N
1*
#795000
0*
#800000
b100 H
bx 1
bx 8
b100 4
b11 N
b1 #
b1 F
b1011101111011010001011011000100 "
b1011101111011010001011011000100 G
1*
#805000
0*
#810000
b100 4
bx 1
bx 8
b0 H
1'
bx (
bx D
1$
b1 #
b1 F
b100 N
1*
#815000
0*
#820000
b100 O
b100 M
b1 H
b1000000000000100000000010010100 )
b1000000000000100000000010010100 5
b10 .
b10 6
1-
b0 1
b0 8
b0 N
0$
b0 #
b0 F
b100 4
1*
#825000
0*
#830000
0-
b0 .
b0 6
b1101111100100010010011100111111 /
b1101111100100010010011100111111 7
b10 H
0'
b100 J
b1000000000000100000000010010100 I
b1 N
1*
#835000
0*
#840000
b11 H
b100 4
b10 N
b1101111100100010010011100111111 K
b1000000000000100000000010010100 %
b1000000000000100000000010010100 E
1*
#845000
0*
#850000
bx 1
bx 8
b100 4
b100 H
b100 #
b100 F
b1101111100100010010011100111111 "
b1101111100100010010011100111111 G
b11 N
1*
#855000
0*
#860000
b0 H
1'
b100 4
bx 1
bx 8
b100 N
1$
b100 #
b100 F
1*
#865000
0*
#870000
b100 O
b1 M
b1 H
b1000000000000000000000001010100 )
b1000000000000000000000001010100 5
b10 .
b10 6
1-
b0 1
b0 8
0$
b0 #
b0 F
b0 N
b100 4
1*
#875000
0*
#880000
0-
b0 .
b0 6
b10000111011111101101100011101101 /
b10000111011111101101100011101101 7
b10 H
0'
b1 N
b1 J
b1000000000000000000000001010100 I
1*
#885000
0*
#890000
b100 4
b11 H
b1000000000000000000000001010100 %
b1000000000000000000000001010100 E
b10000111011111101101100011101101 K
b10 N
1*
#895000
0*
#900000
b100 H
bx 1
bx 8
b100 4
b11 N
b1 #
b1 F
b10000111011111101101100011101101 "
b10000111011111101101100011101101 G
1*
#905000
0*
#910000
b100 4
bx 1
bx 8
b0 H
1'
1$
b1 #
b1 F
b100 N
1*
#915000
0*
#920000
b100 O
b10 M
b1 H
b1000000000000010000000000001100 )
b1000000000000010000000000001100 5
b10 .
b10 6
1-
b0 1
b0 8
b0 N
0$
b0 #
b0 F
b100 4
1*
#925000
0*
#930000
0-
b0 .
b0 6
b11100111011101010000100111001010 /
b11100111011101010000100111001010 7
b10 H
0'
b10 J
b1000000000000010000000000001100 I
b1 N
1*
#935000
0*
#940000
b11 H
b100 4
b10 N
b11100111011101010000100111001010 K
b1000000000000010000000000001100 %
b1000000000000010000000000001100 E
1*
#945000
0*
#950000
bx 1
bx 8
b100 4
b100 H
b10 #
b10 F
b11100111011101010000100111001010 "
b11100111011101010000100111001010 G
b11 N
1*
#955000
0*
#960000
b0 H
1'
b100 4
bx 1
bx 8
b100 N
1$
b10 #
b10 F
1*
#965000
0*
#970000
b100 O
b10 M
b1 H
b1000000000000010000000010010000 )
b1000000000000010000000010010000 5
b10 .
b10 6
1-
b0 1
b0 8
0$
b0 #
b0 F
b0 N
b100 4
1*
#975000
0*
#980000
0-
b0 .
b0 6
b1010010001000011100111110001000 /
b1010010001000011100111110001000 7
b10 H
0'
b1 N
b1000000000000010000000010010000 I
1*
#985000
0*
#990000
b100 4
b11 H
b1000000000000010000000010010000 %
b1000000000000010000000010010000 E
b1010010001000011100111110001000 K
b10 N
1*
#995000
0*
#1000000
b100 H
bx 1
bx 8
b100 4
b11 N
b10 #
b10 F
b1010010001000011100111110001000 "
b1010010001000011100111110001000 G
1*
#1005000
0*
#1010000
b100 4
bx 1
bx 8
b0 H
1'
1$
b10 #
b10 F
b100 N
1*
#1015000
0*
#1020000
b100 O
b1000 M
b1 H
b1000000000000110000000000010000 )
b1000000000000110000000000010000 5
b10 .
b10 6
1-
b0 1
b0 8
b0 N
0$
b0 #
b0 F
b100 4
1*
#1025000
0*
#1030000
0-
b0 .
b0 6
b10110110101101111100110101110100 /
b10110110101101111100110101110100 7
b10 H
0'
b1000 J
b1000000000000110000000000010000 I
b1 N
1*
#1035000
0*
#1040000
b11 H
b100 4
b10 N
b10110110101101111100110101110100 K
b1000000000000110000000000010000 %
b1000000000000110000000000010000 E
1*
#1045000
0*
#1050000
bx 1
bx 8
b100 4
b100 H
b1000 #
b1000 F
b10110110101101111100110101110100 "
b10110110101101111100110101110100 G
b11 N
1*
#1055000
0*
#1060000
b0 H
1'
b100 4
bx 1
bx 8
b100 N
1$
b1000 #
b1000 F
1*
#1065000
0*
#1070000
b100 O
b100 M
b1 H
b1000000000000100000000000001100 )
b1000000000000100000000000001100 5
b10 .
b10 6
1-
b0 1
b0 8
0$
b0 #
b0 F
b0 N
b100 4
1*
#1075000
0*
#1080000
0-
b0 .
b0 6
b1010000010100111101111001111011 /
b1010000010100111101111001111011 7
b10 H
0'
b1 N
b100 J
b1000000000000100000000000001100 I
1*
#1085000
0*
#1090000
b100 4
b11 H
b1000000000000100000000000001100 %
b1000000000000100000000000001100 E
b1010000010100111101111001111011 K
b10 N
1*
#1095000
0*
#1100000
b100 H
bx 1
bx 8
b100 4
b11 N
b100 #
b100 F
b1010000010100111101111001111011 "
b1010000010100111101111001111011 G
1*
#1105000
0*
#1110000
b100 4
bx 1
bx 8
b0 H
1'
1$
b100 #
b100 F
b100 N
1*
#1115000
0*
#1120000
b100 O
b100 M
b1 H
b1000000000000100000000010110000 )
b1000000000000100000000010110000 5
b10 .
b10 6
1-
b0 1
b0 8
b0 N
0$
b0 #
b0 F
b100 4
1*
#1125000
0*
#1130000
0-
b0 .
b0 6
b111011101011100111111110001100 /
b111011101011100111111110001100 7
b10 H
0'
b1000000000000100000000010110000 I
b1 N
1*
#1135000
0*
#1140000
b11 H
b100 4
b10 N
b111011101011100111111110001100 K
b1000000000000100000000010110000 %
b1000000000000100000000010110000 E
1*
#1145000
0*
#1150000
bx 1
bx 8
b100 4
b100 H
b100 #
b100 F
b111011101011100111111110001100 "
b111011101011100111111110001100 G
b11 N
1*
#1155000
0*
#1160000
b0 H
1'
b100 4
bx 1
bx 8
b100 N
1$
b100 #
b100 F
1*
#1165000
0*
#1170000
b100 O
b1000 M
b1 H
b1000000000000110000000011000000 )
b1000000000000110000000011000000 5
b10 .
b10 6
1-
b0 1
b0 8
0$
b0 #
b0 F
b0 N
b100 4
1*
#1175000
0*
#1180000
0-
b0 .
b0 6
b10011110011110101010101010101100 /
b10011110011110101010101010101100 7
b10 H
0'
b1 N
b1000 J
b1000000000000110000000011000000 I
1*
#1185000
0*
#1190000
b100 4
b11 H
b1000000000000110000000011000000 %
b1000000000000110000000011000000 E
b10011110011110101010101010101100 K
b10 N
1*
#1195000
0*
#1200000
b100 H
bx 1
bx 8
b100 4
b11 N
b1000 #
b1000 F
b10011110011110101010101010101100 "
b10011110011110101010101010101100 G
1*
#1205000
0*
#1210000
b100 4
bx 1
bx 8
b0 H
1'
1$
b1000 #
b1000 F
b100 N
1*
#1215000
0*
#1220000
b100 O
b100 M
b1 H
b1000000000000100000000010111100 )
b1000000000000100000000010111100 5
b10 .
b10 6
1-
b0 1
b0 8
b0 N
0$
b0 #
b0 F
b100 4
1*
#1225000
0*
#1230000
0-
b0 .
b0 6
b1110101110000001111111100000111 /
b1110101110000001111111100000111 7
b10 H
0'
b100 J
b1000000000000100000000010111100 I
b1 N
1*
#1235000
0*
#1240000
b11 H
b100 4
b10 N
b1110101110000001111111100000111 K
b1000000000000100000000010111100 %
b1000000000000100000000010111100 E
1*
#1245000
0*
#1250000
bx 1
bx 8
b100 4
b100 H
b100 #
b100 F
b1110101110000001111111100000111 "
b1110101110000001111111100000111 G
b11 N
1*
#1255000
0*
#1260000
b0 H
1'
b100 4
bx 1
bx 8
b100 N
1$
b100 #
b100 F
1*
#1265000
0*
#1270000
b100 O
b10 M
b1 H
b1000000000000010000000001110100 )
b1000000000000010000000001110100 5
b10 .
b10 6
1-
b0 1
b0 8
0$
b0 #
b0 F
b0 N
b100 4
1*
#1275000
0*
#1280000
0-
b0 .
b0 6
b1011101101100001011010101101111 /
b1011101101100001011010101101111 7
b10 H
0'
b1 N
b10 J
b1000000000000010000000001110100 I
1*
#1285000
0*
#1290000
b100 4
b11 H
b1000000000000010000000001110100 %
b1000000000000010000000001110100 E
b1011101101100001011010101101111 K
b10 N
1*
#1295000
0*
#1300000
b100 H
bx 1
bx 8
b100 4
b11 N
b10 #
b10 F
b1011101101100001011010101101111 "
b1011101101100001011010101101111 G
1*
#1305000
0*
#1310000
b100 4
bx 1
bx 8
b0 H
1'
1$
b10 #
b10 F
b100 N
1*
#1315000
0*
